{"afrikaans":"hoofstuk 97 The Power, Fate, Healing koran resitasie, 90+ taal ondertitels","albanian":"kapitulli 97 Fuqia, Fati, Recitimi i Kuranit Shërues, nëntituj mbi 90 gjuhë","amharic":"ምዕራፍ 97 ኃይሉ ፣ ዕጣው ፣ የፈውስ ቁርአን ንባብ ፣ 90+ የቋንቋ ንዑስ ርዕሶች","arabic":"الفصل 97 القوة ، القدر ، شفاء تلاوة القرآن ، 90+ ترجمة لغوية","armenian":"գլուխ 97 Իշխանություն, ateակատագիր, Բուժող քուրան, 90+ լեզվի ենթագրեր","azerbaijani":"fəsil 97 Güc, Tale, Şəfa quran tilavəti, 90+ dil altyazısı","basque":"97. kapitulua The Power, Fate, Healing quran recitation, 90+ hizkuntza azpititulu","belarusian":"Кіраўнік 97 Сіла, лёс, гаючы дэманстрацыі Карана, 90+ моўных субтытраў","bengali":"অধ্যায় 97 শক্তি, ভাগ্য, নিরাময় কোরান আবৃত্তি, 90+ ভাষা উপশিরোনাম","bosnian":"poglavlje 97 Moć, sudbina, iscjeljujuće učenje Kur'ana, titlovi na 90+ jezika","bulgarian":"глава 97 Силата, Съдбата, Лечението на Корана, 90+ езикови субтитри","catalan":"capítol 97 The Power, Fate, Healing recitació de l'alcorà, subtítols en més de 90 idiomes","cebuano":"kapitulo 97 Ang Gahum, Kapalaran, Pag-ayo sa pag-recite sa quran, 90+ nga subtitle sa sinultian","chichewa":"chaputala 97 Mphamvu, Tsogolo, Kuchiritsa quran, mawu am'magazini 90+","chinese(simplified)":"第97章力量，命运，古兰经的朗诵，90多种语言字幕","chinese(traditional)":"第97章力量，命運，古蘭經的朗誦，90多種語言字幕","corsican":"capitulu 97 The Power, Fate, Healing recitation quran, 90+ subtitulos in lingua","croatian":"poglavlje 97 Moć, sudbina, iscjeljujuće učenje Kur'ana, titlovi na 90+ jezika","czech":"kapitola 97 The Power, Fate, Healing Quran recitation, 90+ language subtitles","danish":"kapitel 97 Magt, skæbne, helbredelse af koranrecitation, 90+ sprogundertekster","dutch":"hoofdstuk 97 The Power, Fate, Healing koranrecitatie, 90+ taalondertiteling","english":"chapter 97 The Power, Fate, Healing quran recitation, 90+ language subtitles","esperanto":"ĉapitro 97 La Potenco, Sorto, Resaniga korana deklamado, 90+ lingvaj subtekstoj","estonian":"97. peatükk Koraani vägi, saatus, tervendamine, 90+ keele subtiitrid","filipino":"kabanata 97 Ang Kapangyarihan, Kapalaran, Pagbigkas ng pagbigkas ng quran, 90+ mga subtitle ng wika","finnish":"Luku 97 Voima, kohtalo, parantava koraaniluku, yli 90 kielen tekstitys","french":"chapitre 97 The Power, Fate, Healing Coran récitation, 90+ sous-titres de langue","frisian":"haadstik 97 The Power, Fate, Healing koranresitaasje, 90+ taalûndertiteling","galician":"capítulo 97 The Power, Fate, Healing recitación do corán, subtítulos en máis de 90 idiomas","georgian":"თავი 97 ძალა, ბედი, კურანის განკურნება, 90+ ენის ტიტრები","german":"Kapitel 97 Die Kraft, das Schicksal, die Heilung des Korans, 90+ Sprachuntertitel","greek":"Κεφάλαιο 97 The Power, Fate, Healing quran recitation, 90+ language subtitles","gujarati":"અધ્યાય 97 પાવર, ભાગ્ય, ઉપચાર કુરાન પાઠ, 90+ ભાષા ઉપશીર્ષકો","haitiancreole":"chapit 97 Pouvwa a, sò, gerizon koran resitasyon, 90+ subtitles lang","hausa":"babi na 97 Ikon, Kaddara, karatun kur'ani mai warkarwa, fassarar harshe 90+","hawaiian":"mokuna 97 ka mana, ka hopena, ka hoʻōla quran haʻi ʻana, 90+ mau huaʻōlelo subtitles","hebrew":"פרק 97 הכוח, הגורל, דקלום הקוראן המרפא, כתוביות 90+ לשפה","hindi":"अध्याय 97 द पावर, फेट, हीलिंग क़ुरान सस्वर पाठ, 90+ भाषा उपशीर्षक","hmong":"tshooj 97 Lub Hwj Chim, Txoj hmoo, Kho neeg mob siab tsis nco qab, rov nyeem tau 90+ hom lus","hungarian":"97. fejezet: A hatalom, a sors, a gyógyító Korán szavalata, több mint 90 nyelvű felirat","icelandic":"kafli 97 Krafturinn, örlögin, lækning kóranalesturs, 90+ tungumál texta","igbo":"isi 97 Ike, Fate, Agwọ quran recitation, 90+ ndepụta okwu","indonesian":"bab 97 The Power, Fate, Healing quran pembacaan, 90+ teks bahasa","irish":"caibidil 97 The Power, Fate, Healing quran recitation, 90+ fotheideal teanga","italian":"capitolo 97 The Power, Fate, Healing Quran recitation, 90+ language subtitles","japanese":"第97章力、運命、癒しのコーランの朗読、90以上の言語の字幕","javanese":"bab 97 Kekuwatan, Takdir, Marasake quran, 90+ subtitle basa","kannada":"ಅಧ್ಯಾಯ 97 ಶಕ್ತಿ, ಭವಿಷ್ಯ, ಗುಣಪಡಿಸುವ ಕುರಾನ್ ಪಠಣ, 90+ ಭಾಷೆಯ ಉಪಶೀರ್ಷಿಕೆಗಳು","kazakh":"97-тарау Қуат, Тағдыр, Шипа Құран оқу, 90-нан астам субтитр","khmer":"ជំពូក ៩៧ អំណាចវាសនាការព្យាបាលការចងចាំការអានការអានអក្សរជាអក្សរ ៩០+","kinyarwanda":"igice cya 97 Imbaraga, Iherezo, Gukiza Qoran isoma, 90+ subtitles yururimi","korean":"97 장 힘, 운명, 치유의 꾸란 암송, 90 개 이상의 언어 자막","kurdish(kurmanji)":"beşa 97 Hêz, Qeder, Qencîkirina quranê qenc, 90+ sernavên zimên","kyrgyz":"97-бөлүм Күч, Тагдыр, Шыпаалуу куран окуу, 90дон ашуун субтитр","lao":"ບົດທີ 97 ພະລັງ, ຊະຕາ ກຳ, ການຮັກສາການສົນທະນາສົນທະນາ, ຄຳ ບັນຍາຍພາສາ 90+","latin":"Caput XCVII et virtutis Dei, sors sanitas quran recitatione a solo, imago lingua 90+","latvian":"97. nodaļa Spēks, liktenis, dziedinošā korāna deklamēšana, vairāk nekā 90 valodu subtitri","lithuanian":"97 skyrius „Galia, likimas“, „Korano deklamavimas“, subtitrai daugiau nei 90 kalbų","luxembourgish":"Kapitel 97 D'Kraaft, d'Schicksal, d'Healing Koran Recitatioun, 90+ Sprooch Ënnertitelen","macedonian":"поглавје 97 Моќта, судбината, лекување на Курани со лекување, преводи со повеќе од 90 јазици","malagasy":"toko 97 The Power, Fate, Healing quran recitation, 90+ dikanteny dikanteny","malay":"bab 97 Kekuatan, Nasib, bacaan quran Penyembuhan, 90+ sari kata bahasa","malayalam":"അധ്യായം 97 പവർ, വിധി, രോഗശാന്തി ഖുറാൻ പാരായണം, 90+ ഭാഷാ സബ്ടൈറ്റിലുകൾ","maltese":"kapitlu 97 The Power, Fate, Healing recitation quran, 90+ language subtitles","maori":"pene 97 Te Mana, Takoha, Te whakaora i te whakahua quran, 90+ hauraro reo","marathi":"धडा The The पॉवर, भाग्य, उपचार हा कुरान पठण, 90+ भाषा उपशीर्षके","mongolian":"97-р бүлэг Хүч чадал, Хувь тавилан, Эдгэрлийн куран уншлага, 90 гаруй хэл дээрх хадмалтай","myanmar(burmese)":"အခန်း ၉၇ ပါဝါ၊ ကံကြမ္မာ၊ ကုရ်အာန်ကျမ်းတော်မြတ်ကုရ်အာန်ကိုရွတ်ဆိုခြင်း၊ ဘာသာစကား ၉၀ ကျော်","nepali":"अध्याय The The पावर, भाग्य, हिलिंग कुरान पाठ, + ०+ भाषा उपशीर्षक","norwegian":"kapittel 97 The Power, Fate, Healing quran recitation, 90+ språk teksting","odia(oriya)":"ଅଧ୍ୟାୟ 97 ଶକ୍ତି, ଭାଗ୍ୟ, ଆରୋଗ୍ୟକାରୀ କୁରାନ ପାଠ, 90+ ଭାଷା ସବ୍ଟାଇଟ୍ |","pashto":"chapter 97 فصل ، ځواک ، برخلیک ، د قران پاک تلاوت ، 90+ ژبې فرعي سرلیکونه","persian":"فصل 97 قدرت ، سرنوشت ، شفابخشی قرآن ، زیرنویس 90+ زبان","polish":"rozdział 97 Moc, przeznaczenie, uzdrawiająca recytacja Koranu, napisy w ponad 90 językach","portuguese":"capítulo 97 O poder, destino, recitação curativa do Alcorão, mais de 90 legendas em idiomas","punjabi":"ਅਧਿਆਇ 97 ਸ਼ਕਤੀ, ਕਿਸਮਤ, ਹੀਲਿੰਗ ਕੁਰਾਨ ਪਾਠ, 90+ ਭਾਸ਼ਾ ਉਪਸਿਰਲੇਖ","romanian":"capitolul 97 Puterea, Soarta, Recitarea Coranului Vindecător, subtitrări în peste 90 de limbi","russian":"Глава 97 Сила, Судьба, Исцеляющее чтение Корана, 90+ языковых субтитров","samoan":"mataupu 97 Le Malosiaga, Faʻataʻitaʻiga, Faʻamalologa quran recitation, 90+ gagana ulutala","scotsgaelic":"caibideil 97 The Power, Fate, Healing quran aithris, fo-thiotalan cànain 90+","serbian":"поглавље 97 Моћ, судбина, лековито рецитовање Кур'ана, титлови на 90+ језика","sesotho":"khaolo ea 97 The Power, Phello e sa Qojoeng, Healing quran pheta, 90+ subtitles la puo","shona":"chitsauko 97 Simba, Gumo, Kuporesa quran kudzokorora, 90+ mitauro yemusoro","sindhi":"باب 97 طاقت ، قسمت ، شفا بخش قرآن مجيد ، 90+ زبان جا عنوان","sinhala":"97 වන පරිච්ඡේදය බලය, ඉරණම, සුව කිරීමේ කුරාන් පාරායනය, 90+ භාෂා උපසිරැසි","slovak":"kapitola 97 Sila, osud, liečenie koránu, 90+ jazykových titulkov","slovenian":"poglavje 97 Moč, usoda, citiranje korana, 90+ jezikovnih podnapisov","somali":"cutubka 97aad Awoodda, Qaddarka, Qur'aan akhriska, 90 + subtitles-ka","spanish":"Capítulo 97 La recitación del Corán Poder, Destino y Sanación, más de 90 subtítulos en idiomas","sundanese":"bab 97 Kakuatan, Takdir, Penyembuhan al-quran, 90+ terjemahan bahasa","swahili":"sura ya 97 Usomaji wa quran wa Nguvu, Hatima, Uponyaji, manukuu 90+ ya lugha","swedish":"kapitel 97 The Power, Fate, Healing quran recitation, 90+ språktexter","tajik":"боби 97 Қудрат, Тақдир, Шифо қироати қуръон, 90+ субтитрҳо","tamil":"அத்தியாயம் 97 சக்தி, விதி, குணப்படுத்தும் குர்ஆன் பாராயணம், 90+ மொழி வசன வரிகள்","tatar":"97 бүлек Көч, язмыш, шифалы куран укуы, 90+ тел субтитрлары","telugu":"అధ్యాయం 97 శక్తి, విధి, హీలింగ్ ఖురాన్ పారాయణం, 90+ భాషా ఉపశీర్షికలు","thai":"บทที่ 97 พลังโชคชะตาการบรรยายอัลกุรอานบทบรรยาย 90+ ภาษา","turkish":"97.Bölüm Güç, Kader, İyileştirici kuran okuması, 90'dan fazla dilde altyazı","turkmen":"97-nji bap Güýç, ykbal, bejeriş şygary, 90+ dil subtitrleri","ukrainian":"Розділ 97 Сила, доля, зцілення читання Корану, 90+ мовних субтитрів","urdu":"باب 97 طاقت ، قسمت ، شفا بخش قرآن ، تلاوت ، 90+ زبان کے ذیلی عنوانات","uyghur":"97-باب كۈچ ، تەقدىر ، شىپالىق قۇرئان تىلاۋەت قىلىش ، 90+ تىل تارماق","uzbek":"97-bob. Quvvat, Taqdir, Davolash Qur'on tilovati, 90+ tilidagi subtitrlar","vietnamese":"Chương 97 Sức mạnh, Số phận, Sự đọc kinh quran chữa bệnh, hơn 90 phụ đề ngôn ngữ","welsh":"pennod 97 Y Pwer, Tynged, Llefaru quran llefaru, is-deitlau iaith 90+","xhosa":"Isahluko 97 Amandla, ikamva, lokuphilisa quran, 90+ imibhalo engezantsi","yiddish":"קאַפּיטל 97 די מאַכט, גורל, היילונג קווראַן רעסיטאַטיאָן, 90+ שפּראַך סאַבטייטאַלז","yoruba":"ori 97 Agbara, Ayanmọ, Iwosan quran imularada, awọn atunkọ ede 90 +","zulu":"isahluko 97 Amandla, Isiphetho, Ukuphulukisa quran, imibhalo engezansi yolimi engama-90"}